{
  "title": "PM grieves over martyrdom of children injured in Khuzdar bus attack",
  "author": null,
  "content": "ISLAMABAD, May 25 (APP):Prime Minister Muhammad Shehbaz Sharif Sunday expressed grief and sorrow over the martyrdom of two children who sustained injuries in a cowardly attack, on a school bus in Khuzdar, by terrorists patronized by India .\nHe expressed sympathy with the parents of the children.\nThe attack on the innocent children in a school bus by terrorists patronized by India was a self-evident proof of their animosity against education in Balochistan, he added.\nHe said the terrorists crossed all limits of barbarity.\n“We will not rest till meting out punishment to the terrorists patronized by India,” he added.\nThe prime minister said all possible steps will be taken to foil nefarious designs of the terrorists patronized by India to undermine peace in Balochistan.\nThe terrorists who targetted Pakistan’s future – the small and innocent children, will meet their end, he continued.\n“My and nation’s sympathies are with the families of the innocent children who fell victim to the cruelty,” he said adding the security forces and the government of Pakistan were determined and united for the complete elimination of terrorism from the country.\n(adsbygoogle=window.adsbygoogle||[]).push({});",
  "tags": [],
  "categories": [],
  "image": null,
  "retrievedAt": "2025-08-27T15:52:05.466Z",
  "source": "APP",
  "link": "https://www.app.com.pk/national/pm-grieves-over-martyrdom-of-children-injured-in-khuzdar-bus-attack/",
  "dateList": "2025-05-25",
  "date_published": "2025-05-25T14:59:00.000Z"
}
