{
  "title": "PM urges int’l community to reinforce Afghan peace efforts",
  "link": "https://www.app.com.pk/national/pm-urges-intl-community-to-reinforce-afghan-peace-efforts/",
  "date_published": "2021-08-12T15:43:00.000Z",
  "source": "APP",
  "content": "ISLAMABAD, Aug 12 (APP): Prime Minister Imran Khan Thursday reaffirmed Pakistan’s resolve to support the Afghan peace process and urged the international community to reinforce those efforts as peace in Afghanistan was a shared responsibility.\nThe prime minister, in a meeting with Foreign Minister of Iraq Dr. Fuad Hussein, who called on him here, outlined Pakistan’s consistent support for an inclusive, broad-based and comprehensive political settlement.\nThe prime minister underscored the importance of resolving issues through dialogue and diplomacy.\nOn Afghanistan, he reiterated that there was no military solution and that a negotiated political solution was the only way forward.\nThe prime minister extended warm welcome to the foreign minister and reaffirmed Pakistan’s close fraternal ties with Iraq, founded on strong affinities of faith and culture.\nHe appreciated Iraq’s resolute efforts to rebuild the country and wished well for the upcoming parliamentary elections.\nWhile discussing various aspects of bilateral relations, the prime minister underscored the importance accorded by Pakistan to further deepening and broadening mutual cooperation with Iraq in diverse fields.\nImran Khan also reiterated his invitation extended to the Prime Minister of Iraq and expressed the hope that the visit would take place at an early date.\nThanking the prime minister for extending warm hospitality to his delegation, Foreign Minister Dr. Fuad Hussein conveyed cordial greetings of the Iraqi leadership.\nHe affirmed Iraq’s desire to forge stronger relationship with Pakistan in pursuance of the vision of the leadership of the two countries.\nThanking the prime minister for his invitation to the Iraqi prime minister, Foreign Minister Dr. Fuad Hussein conveyed invitation on behalf of the Iraqi Prime Minister to Prime Minister Imran Khan to visit Iraq.\nThe foreign minister also highlighted Iraq’s efforts to defuse tensions in the region and promote cooperative ties among regional countries. The Prime Minister expressed Pakistan’s support for these endeavors.",
  "retrievedAt": "2025-08-11T21:04:25.375Z"
}
