{
  "title": "KSrelief distributes 500 food baskets in Pakistan",
  "link": "https://www.app.com.pk/national/ksrelief-distributes-500-food-baskets-in-pakistan/",
  "date_published": "2024-01-23T16:37:00.000Z",
  "source": "APP",
  "content": "ISLAMABAD, Jan 23 (APP):The King Salman Humanitarian Aid and Relief Center (KSrelief) continued distributing food baskets in Pakistan as part of the third phase of the project to support food security in Pakistan for the year 2024.\nFive hundred food baskets were distributed in Malakand District of Khyber Pakhtunkhwa province, benefiting 3,500 vulnerable people in flood-affected areas, SPA reported.\nThe assistance comes within the relief projects provided by the Kingdom of Saudi Arabia through its humanitarian body, KSrelief, to enhance food security in Pakistan amid its humanitarian crisis.\n(adsbygoogle=window.adsbygoogle||[]).push({});",
  "retrievedAt": "2025-08-10T23:50:23.418Z"
}
