{
  "title": "Saudi ambassador calls on minister for Power",
  "link": "https://www.app.com.pk/national/saudi-ambassador-calls-on-minister-for-power/",
  "date_published": "2024-03-25T17:44:00.000Z",
  "source": "APP",
  "content": "ISLAMABAD, Mar 25 (APP): The Saudi Ambassador to Pakistan, Nawaf bin Said Al-Malki Monday called on Federal Minister for Power, Sardar Awais Ahmad Khan Leghari.\nDuring the meeting, the minister acknowledged the steadfast support of the brotherly country in all challenging situations, said a news release.\nAwais Leghari highlighted various investment opportunities, particularly in the transmission sector, and assured the ambassador of investor-friendly policies under the current government.\nThe ambassador pledged support for Saudi businesses to explore Pakistan’s investment potential.",
  "retrievedAt": "2025-08-11T01:33:01.988Z"
}
