{
  "title": "Caretaker PM to represent Pakistan in COP-28 high-level segment",
  "link": "https://www.app.com.pk/national/caretaker-pm-to-represent-pakistan-in-cop-28-high-level-segment/",
  "date_published": "2023-11-22T11:30:00.000Z",
  "source": "APP",
  "content": "ISLAMABAD, Nov 22 (APP):Caretaker Prime Minister Anwaar-ul-Haq Kakar will represent Pakistan during the high level segment of 28th Conference of Parties (COP-28) being held in the United Arab Emirates on December 01-02.\nThe prime minister chaired an inter-provincial review meeting with regard to the COP-28. The meeting was attended by the caretaker federal ministers for finance, foreign affairs, climate change and planning, and relevant officials, the PM Office Media Wing said in a press release.\nPM Kakar said that climate change was an issue of national endurance for the countries like Pakistan and observed that Pakistan was playing a positive role in the global climate debate through climate diplomacy.\nHe said that despite its less than one percent imprints in the global climate change factors, Pakistan was amongst the countries hugely affected by the changes.\nOne third of the country’s population was badly affected by the climate induced floods, he added.\nThe prime minister also lauded the relevant institutions and organizations of the country for their best role in the reconstruction efforts in the post-flood period.\nHe also directed the relevant authorities to make full preparations for representing Pakistan’s stance during the COP-28 on climate finance and other issues effectively.",
  "retrievedAt": "2025-08-11T10:37:44.632Z"
}
