{
  "title": "Imran Khan wants to save his skin by spreading anarchy: Marriyum",
  "link": "https://www.app.com.pk/national/imran-khan-wants-to-save-his-skin-by-spreading-anarchy-marriyum/",
  "date_published": "2022-09-03T18:15:00.000Z",
  "source": "APP",
  "content": "ISLAMABAD, Sep 03 (APP):Minister for Information and Broadcasting Marriyum Aurangzeb on Saturday said Imran Khan wanted to save his skin in corruption cases by spreading anarchy in the country.\n“Imran Khan has launched Tehreek-e-fasad (movement to spread anarchy) to save himself in the corruption cases,” the minister said in a news statement while reacting to the Pakistan Tehreek-e-Insaf chairman’s address to a public gathering in Bahawalpur.\nThe people were facing flash floods, but Imran Khan did only think about himself and his politics, she added.\nThe minister said Imran Khan seemed to be obsessed with Prime Minister Shehbaz Sharif and Maryam Nawaz during his visit to the South Punjab.\nInstead of announcing any relief for the flood affectees, Imran Khan only did politicking during his visit to the South Punjab which was under water, she added.\nShe said Imran Khan wanted to introduce a system in the country which could help him avenge his political opponents.\nMarriyum said the coalition government had foiled Imran Khan’s conspiracy to turn Pakistan into Sri Lanka. The country was witnessing economic and political stability by the grace of Allah Almighty.",
  "retrievedAt": "2025-08-11T15:30:50.168Z"
}
