{
  "title": "Railways minister inquires after health of injured at Sheikh Zayed Hospital RYK",
  "link": "https://www.app.com.pk/national/railways-minister-inquires-after-health-of-injured-at-sheikh-zayed-hospital-ryk/",
  "date_published": "2021-06-07T17:27:00.000Z",
  "source": "APP",
  "content": "LAHORE, RAHIM YAR KHAN, Jun 7 (APP): Railways Minister Azam Khan Swati on Monday inquired after health of the injured of the train accident at emergency ward of the Sheikh Zayed Hospital here and reviewed medical facilities being provided to them.\nTalking to the media, the minister said there was no substitute for precious human lives, adding that in this hour of the need the federal government and Pakistan Railways were with the affected families.\nHe said all possible medical facilities would be provided to the injured. He added that all senior officers of the Railways had been directed to remain in hospitals till the complete recovery of the last injured.\nThe minister assured that the responsible would not be spared and said punishment would start from seniors and no junior employee would be made a scapegoat.\nHe said the steps taken by the Punjab government to provide rescue operations and medical treatment to the injured were commendable. He appreciated Chief Minister Punjab Sardar Usman Buzdar, and rescue agencies for providing the best medical aid to the injured.\nHe thanked the highways, Pak Army, Rangers, the Punjab government, Rescue 1122 and others departments for participating in the rescue and relief operation with full national spirit. He added that all departments had shown national responsibility and reached the needy brothers without wasting a moment.",
  "retrievedAt": "2025-08-11T20:49:13.540Z"
}
