[
  {
    "title": "Govt to reform public sector hospitals as per int’l standards: PM",
    "link": "https://www.app.com.pk/national/govt-to-reform-public-sector-hospitals-as-per-intl-standards-pm/",
    "date_published": "2019-05-18T12:58:00.000Z"
  },
  {
    "title": "PM grieved over demise of Speaker Balochistan Assembly’s father",
    "link": "https://www.app.com.pk/national/pm-grieved-over-demise-of-speaker-balochistan-assemblys-father/",
    "date_published": "2019-05-18T11:41:00.000Z"
  },
  {
    "title": "COAS visits troops on forwards posts along Pak-Afghan Border",
    "link": "https://www.app.com.pk/national/coas-visits-troops-on-forwards-posts-along-pak-afghan-border/",
    "date_published": "2019-05-18T11:37:00.000Z"
  },
  {
    "title": "New laws, systems to be compatible with traditions of merged tribal areas: PM",
    "link": "https://www.app.com.pk/national/new-laws-systems-to-be-compatible-with-traditions-of-merged-tribal-areas-pm/",
    "date_published": "2019-05-18T11:37:00.000Z"
  },
  {
    "title": "PM directs KP cabinet for action against hoarders, ensure price control",
    "link": "https://www.app.com.pk/national/pm-directs-kp-cabinet-for-action-against-hoarders-ensure-price-control/",
    "date_published": "2019-05-18T11:36:00.000Z"
  },
  {
    "title": "President condoles with Speaker Balochistan Abdul Quddus on demise of his father Abdul Majeed Bizenjo",
    "link": "https://www.app.com.pk/national/president-condoles-with-speaker-balochistan-abdul-quddus-on-demise-of-his-father-abdul-majeed-bizenjo/",
    "date_published": "2019-05-18T10:40:00.000Z"
  },
  {
    "title": "PM in Peshawar to attend SKMCH fundraiser; meet leadership",
    "link": "https://www.app.com.pk/national/pm-in-peshawar-to-attend-skmch-fundraiser-meet-leadership/",
    "date_published": "2019-05-18T07:50:00.000Z"
  },
  {
    "title": "PM due in Peshawar to meet leadership, attend fundraiser",
    "link": "https://www.app.com.pk/national/pm-due-in-peshawar-to-meet-leadership-attend-fundraiser/",
    "date_published": "2019-05-18T07:06:00.000Z"
  },
  {
    "title": "Govt moving forward on policies, reforms for economic revival: Firdous",
    "link": "https://www.app.com.pk/national/govt-moving-forward-on-policies-reforms-for-economic-revival-firdous/",
    "date_published": "2019-05-18T07:06:00.000Z"
  },
  {
    "title": "Dr Firdous meets senior journalists",
    "link": "https://www.app.com.pk/national/dr-firdous-meets-senior-journalists/",
    "date_published": "2019-05-18T07:05:00.000Z"
  },
  {
    "title": "PR to run five Eid Special trains: Sheikh Rashid",
    "link": "https://www.app.com.pk/national/pr-to-run-five-eid-special-trains-sheikh-rashid/",
    "date_published": "2019-05-18T06:09:00.000Z"
  },
  {
    "title": "Firdous regrets opposition’s conspiracy against elected govt in Ramazan",
    "link": "https://www.app.com.pk/national/firdous-regrets-oppositions-conspiracy-against-elected-govt-in-ramazan/",
    "date_published": "2019-05-18T05:07:00.000Z"
  },
  {
    "title": "Omar for zero tolerance against gas pilferage",
    "link": "https://www.app.com.pk/national/omar-for-zero-tolerance-against-gas-pilferage/",
    "date_published": "2019-05-18T02:53:00.000Z"
  },
  {
    "title": "Sanjrani condoles with Abdul Quddus on demise of his father",
    "link": "https://www.app.com.pk/national/sanjrani-condoles-with-abdul-quddus-on-demise-of-his-father/",
    "date_published": "2019-05-17T23:08:00.000Z"
  },
  {
    "title": "Pakistan Post opens 41 rest houses for tourists",
    "link": "https://www.app.com.pk/national/pakistan-post-opens-41-rest-houses-for-tourists/",
    "date_published": "2019-05-17T23:07:00.000Z"
  },
  {
    "title": "Governor Punjab hosts Iftar dinner to Railway employees",
    "link": "https://www.app.com.pk/national/governor-punjab-hosts-iftar-dinner-to-railway-employees/",
    "date_published": "2019-05-17T23:07:00.000Z"
  },
  {
    "title": "AJK PM, Info Minister condole sad demise of Kaira’s son",
    "link": "https://www.app.com.pk/national/ajk-pm-info-minister-condole-sad-demise-of-kairas-son/",
    "date_published": "2019-05-17T23:04:00.000Z"
  },
  {
    "title": "CM distributes Rs 5.4mln cheques among victims",
    "link": "https://www.app.com.pk/national/cm-distributes-rs-5-4mln-cheques-among-victims/",
    "date_published": "2019-05-17T23:03:00.000Z"
  },
  {
    "title": "Traditions, culture of tribal people to be considered in making policies: Governor",
    "link": "https://www.app.com.pk/national/traditions-culture-of-tribal-people-to-be-considered-in-making-policies-governor/",
    "date_published": "2019-05-17T23:02:00.000Z"
  }
]
