{
  "title": "River Indus continues to flow in low, medium flood: FFC",
  "link": "https://www.app.com.pk/national/river-indus-continues-to-flow-in-low-medium-flood-ffc/",
  "date_published": "2024-09-01T10:37:00.000Z",
  "source": "APP",
  "content": "ISLAMABAD, Sep 01 (APP):The Federal Flood Commission (FFC) has said that presently, River Indus is experiencing Low Flood at Chashma and in Medium Flood at Kotri Barrage while the rest of the major rivers in the Indus River System (i.e. Rivers Jhelum, Chenab, Ravi, and Sutlej) are discharging normal flows.\nAccording to the FFC report on Sunday, Tarbela Reservoir is maintaining its Maximum Conservation Level (MCL) of 1550.00 feet in last 13 days. In contrast, Mangla Reservoir is currently at an elevation of 1222.05 feet, which is 19.95 feet below its MCL i.e. 1242 feet. Combined live storage of the country’s major reservoirs (Tarbela, Chashma & Mangla) stands at 11.803 MAF (88.39% of the total storage capacity of 13.354 MAF).\nAccording to the Flood Forecasting Division (FFD), Lahore, Cyclonic Storm (CS) “ASNA” lies in Arabian Sea at approximately 240 km South of Gwadar and is likely to become insignificant for Pakistan. Yesterday’s trough of Westerly Wave over Northeastern Iran today lies over Northern parts of Afghanistan.\nLight moist currents from the Bay of Bengal are penetrating the upper parts of Pakistan. However, it will become moderate during the next two days. Yesterday’s well-marked low over Southeastern Odisha (India) lies over Southern Odisha (India) and adjoining Andhra Pradesh (India). Weak Seasonal Low lies over Northern Balochistan.\nFFD Lahore has predicted, scattered thunderstorm rain over Khyber-Pakhtunkhwa (Peshawar, Kohat & Bannu Division), Balochistan (Zhob & Makran Division) along with upper catchments of river Kabul during the next 24 hours. Isolated thunderstorm rain of moderate intensity is expected over the upper catchments of all the other major rivers during the said period.\nA fresh spell of Moderate Rainfall, with Isolated Heavy Showers, Islamabad, Punjab and Khyber Pakhtunkhwa along with upper catchments of all the major rivers. No significant increase is excepted in any of the major rivers of the Indus River System.\n(adsbygoogle=window.adsbygoogle||[]).push({});",
  "retrievedAt": "2025-08-10T20:38:31.482Z"
}
