{
  "title": "Omani Military Chief of Staff visits NHQ",
  "link": "https://www.app.com.pk/national/omani-military-chief-of-staff-visits-nhq/",
  "date_published": "2023-08-07T13:09:00.000Z",
  "source": "APP",
  "content": "ISLAMABAD, Aug 7 (APP): Chief of Staff Sultan Armed Forces Oman, Vice Admiral Abdullah Bin Khamis Al Raisi on Monday visited Naval Headquarters (NHQ) here and called on Chief of the Naval Staff Admiral Muhammad Amjad Khan Niazi.\nDuring the meeting, matters of mutual interest including bilateral collaborations and regional maritime security environment were discussed, a Pakistan Navy news release said.\nThe Naval Chief highlighted Pakistan Navy’s initiatives to ensure maritime security and peace in the region through Regional Maritime Security Patrols.\nThe visiting Admiral acknowledged and lauded Pakistan Navy’s efforts and commitments in support of collaborative maritime security in the region.\nOman is a maritime neighbour of Pakistan and both countries have a common maritime boundary.\nThe ships of both countries routinely operate close to each other’s coasts and accordingly provide support to each other in terms of medical evacuations, cooperation in maritime law enforcement and logistics support.\nBoth the navies enjoy very close relations and are very forth coming to support each other.\nThe visit of Chief of Staff Sultan Armed Forces Oman will further enhance bilateral collaboration between the two countries.",
  "retrievedAt": "2025-08-11T09:06:00.895Z"
}
