{
  "title": "Sheikh Rashid’s elder brother dies",
  "link": "https://www.app.com.pk/national/sheikh-rashids-elder-brother-dies/",
  "date_published": "2021-11-17T04:51:00.000Z",
  "source": "APP",
  "content": "ISLAMABAD, Nov 17 (APP): The elder brother of  Sheikh Rashid Ahmed, Minister for Interior, Lala Sheikh Rafeeq Qamar died.  His nimaz-e janaza will be offered today (Wednesday) at 6:00 pm at Kot Radha Kishen, the minister tweeted.\n(adsbygoogle=window.adsbygoogle||[]).push({});",
  "retrievedAt": "2025-08-11T21:37:26.862Z"
}
