{
  "title": "PM always works for poor people’s welfare: Shibli",
  "link": "https://www.app.com.pk/national/pms-always-worked-for-poor-people-shibli/",
  "date_published": "2021-01-09T17:08:00.000Z",
  "source": "APP",
  "content": "ISLAMABAD, Jan 9 (APP): Federal Minister for Information and Broadcasting Senator Shibli Faraz on Saturday Prime Minister Imran Khan had always thought for the welfare of poor people.\nThe initiatives like Ehsaas Programme, Health Cards, and shelter homes taken by Pakistan Tehreek-e-Insaf government manifested his vision of improving the living conditions of the underprivileged segments of the society, he said while talking to a private news channel.\nThe minister said terrorism to a great extent had been eliminated from the country due to effective policies of the government and operations of the law enforcing agencies.\nHe said the occasional terror acts like Hazara miners’ massacre were still occurring as India was trying to create unrest in Pakistan by promoting sectarianism. India was even financing terrorists and other extremist elements.\nThe government was, however, committed to root out the terrorist networks completely so that incidents Machh killings might not occur in future.\nTo a question, Shibli Faraz said the Pakistan Democratic Movement’s leadership had themselves buried their politics. There were fissures in the opposition alliance, he added.\nHe said the politics of Pakistan Muslim League-Nawaz’s leaders based on lies and hypocrisy as they tried to do politicking over the Machh incident.\nTo another query. he said Pakistan and Saudi Arabia were enjoying cordial relations. The Saudi foreign minister was expected to visit Pakistan soon, he added.",
  "retrievedAt": "2025-08-11T20:13:33.473Z"
}
